LICENCE.txt
MANIFEST.in
README.rst
setup.cfg
setup.py
chalumo/__init__.py
chalumo/diff.py
chalumo/discovery.py
chalumo/exceptions.py
chalumo/fixer.py
chalumo/logger.py
chalumo/parser.py
chalumo/reformat.py
chalumo.egg-info/PKG-INFO
chalumo.egg-info/SOURCES.txt
chalumo.egg-info/dependency_links.txt
chalumo.egg-info/entry_points.txt
chalumo.egg-info/requires.txt
chalumo.egg-info/top_level.txt
chalumo.egg-info/zip-safe
chalumo/cli/__init__.py
chalumo/cli/base.py
chalumo/cli/diff.py
chalumo/cli/entrypoint.py
chalumo/cli/reformat.py
chalumo/cli/version.py
chalumo/old_cli/__init__.py
chalumo/old_cli/entrypoint.py
chalumo/processors/__init__.py
chalumo/processors/django.py