Metadata-Version: 2.1
Name: chalumo
Version: 0.4.1
Summary: A simple script to lint, diff or reformat HTML 'class' attribute values
Home-page: https://github.com/sveetch/chalumo
Author: David Thenon
Author-email: sveetch@gmail.com
License: MIT
Keywords: Python
Classifier: Development Status :: 2 - Pre-Alpha
Classifier: Intended Audience :: Developers
Classifier: License :: OSI Approved :: MIT License
Classifier: Natural Language :: English
Classifier: Programming Language :: Python :: 3
Classifier: Programming Language :: Python :: 3.7
Classifier: Programming Language :: Python :: 3.8
Classifier: Programming Language :: Python :: 3.9
Classifier: Framework :: Django
Classifier: Framework :: Django :: 3.0
Classifier: Framework :: Django :: 3.1
Classifier: Framework :: Django :: 3.2
Classifier: Framework :: Django :: 4.0
Provides-Extra: dev
Provides-Extra: quality
Provides-Extra: doc
License-File: LICENCE.txt
